{
"meta":{"test_sets":[],"test_metrics":[],"learn_metrics":[{"best_value":"Min","name":"Logloss"}],"launch_mode":"Train","parameters":"","iteration_count":230,"learn_sets":["learn"],"name":"experiment"},
"iterations":[
{"learn":[0.6649168894],"iteration":0,"passed_time":0.08862033451,"remaining_time":20.2940566},
{"learn":[0.6375230777],"iteration":1,"passed_time":0.1799960913,"remaining_time":20.51955441},
{"learn":[0.6118459087],"iteration":2,"passed_time":0.3173498419,"remaining_time":24.0128047},
{"learn":[0.5919537418],"iteration":3,"passed_time":0.3680752142,"remaining_time":20.7962496},
{"learn":[0.5713741776],"iteration":4,"passed_time":0.4705093638,"remaining_time":21.17292137},
{"learn":[0.5528402035],"iteration":5,"passed_time":0.5900633776,"remaining_time":22.02903276},
{"learn":[0.533605366],"iteration":6,"passed_time":0.6712903959,"remaining_time":21.38539404},
{"learn":[0.5145765831],"iteration":7,"passed_time":0.7725442304,"remaining_time":21.43810239},
{"learn":[0.4994465461],"iteration":8,"passed_time":0.8783157208,"remaining_time":21.56753048},
{"learn":[0.4844728618],"iteration":9,"passed_time":1.052891935,"remaining_time":23.16362258},
{"learn":[0.4720622944],"iteration":10,"passed_time":1.187820235,"remaining_time":23.64842105},
{"learn":[0.4590648643],"iteration":11,"passed_time":1.413473637,"remaining_time":25.6781044},
{"learn":[0.4481775802],"iteration":12,"passed_time":1.536418447,"remaining_time":25.64636946},
{"learn":[0.4381223273],"iteration":13,"passed_time":1.733489388,"remaining_time":26.74526484},
{"learn":[0.4287430613],"iteration":14,"passed_time":1.897972908,"remaining_time":27.20427835},
{"learn":[0.4201655016],"iteration":15,"passed_time":2.022872107,"remaining_time":27.05591443},
{"learn":[0.4120917969],"iteration":16,"passed_time":2.16449654,"remaining_time":27.11986841},
{"learn":[0.4034167866],"iteration":17,"passed_time":2.312875196,"remaining_time":27.24053009},
{"learn":[0.3960477745],"iteration":18,"passed_time":2.556236114,"remaining_time":28.38767474},
{"learn":[0.3903840718],"iteration":19,"passed_time":2.703746495,"remaining_time":28.3893382},
{"learn":[0.3849346217],"iteration":20,"passed_time":2.789837493,"remaining_time":27.76552552},
{"learn":[0.3787517475],"iteration":21,"passed_time":2.884848451,"remaining_time":27.27493081},
{"learn":[0.3730070929],"iteration":22,"passed_time":2.973212083,"remaining_time":26.75890875},
{"learn":[0.3693724815],"iteration":23,"passed_time":3.09734133,"remaining_time":26.58551308},
{"learn":[0.3652307771],"iteration":24,"passed_time":3.195824471,"remaining_time":26.20576066},
{"learn":[0.3615941612],"iteration":25,"passed_time":3.289215373,"remaining_time":25.80768985},
{"learn":[0.3582889083],"iteration":26,"passed_time":3.386459085,"remaining_time":25.46115534},
{"learn":[0.3543258121],"iteration":27,"passed_time":3.815500419,"remaining_time":27.52611016},
{"learn":[0.3510048828],"iteration":28,"passed_time":4.051079474,"remaining_time":28.07817153},
{"learn":[0.3478589895],"iteration":29,"passed_time":4.159137424,"remaining_time":27.72758283},
{"learn":[0.3451900699],"iteration":30,"passed_time":4.306034878,"remaining_time":27.64196583},
{"learn":[0.3426060341],"iteration":31,"passed_time":4.409958611,"remaining_time":27.2866189},
{"learn":[0.3401888877],"iteration":32,"passed_time":4.497299499,"remaining_time":26.84751519},
{"learn":[0.3377107319],"iteration":33,"passed_time":4.567082298,"remaining_time":26.32788619},
{"learn":[0.3344192023],"iteration":34,"passed_time":4.680553146,"remaining_time":26.07736753},
{"learn":[0.3321181384],"iteration":35,"passed_time":4.777909411,"remaining_time":25.74762294},
{"learn":[0.3299777961],"iteration":36,"passed_time":4.858106919,"remaining_time":25.34093609},
{"learn":[0.3275639905],"iteration":37,"passed_time":4.944914044,"remaining_time":24.98482885},
{"learn":[0.3251973941],"iteration":38,"passed_time":5.029729557,"remaining_time":24.63277809},
{"learn":[0.323383712],"iteration":39,"passed_time":5.11385544,"remaining_time":24.29081334},
{"learn":[0.3210779965],"iteration":40,"passed_time":5.229102015,"remaining_time":24.1048849},
{"learn":[0.3197590461],"iteration":41,"passed_time":5.306212945,"remaining_time":23.75161985},
{"learn":[0.3179323602],"iteration":42,"passed_time":5.376611416,"remaining_time":23.38200779},
{"learn":[0.3158230366],"iteration":43,"passed_time":5.493242084,"remaining_time":23.22143245},
{"learn":[0.3140041118],"iteration":44,"passed_time":5.627937315,"remaining_time":23.13707563},
{"learn":[0.3125865286],"iteration":45,"passed_time":5.7578885,"remaining_time":23.031554},
{"learn":[0.3109087171],"iteration":46,"passed_time":5.88376374,"remaining_time":22.90912265},
{"learn":[0.3096691766],"iteration":47,"passed_time":5.97211462,"remaining_time":22.64426793},
{"learn":[0.3083728927],"iteration":48,"passed_time":6.09214987,"remaining_time":22.50365564},
{"learn":[0.306974815],"iteration":49,"passed_time":6.182170131,"remaining_time":22.25581247},
{"learn":[0.3058812449],"iteration":50,"passed_time":6.303226637,"remaining_time":22.12308957},
{"learn":[0.3046092465],"iteration":51,"passed_time":6.383001642,"remaining_time":21.84950562},
{"learn":[0.3032248921],"iteration":52,"passed_time":6.481746801,"remaining_time":21.64658837},
{"learn":[0.3018619963],"iteration":53,"passed_time":6.598081512,"remaining_time":21.50485826},
{"learn":[0.300824707],"iteration":54,"passed_time":6.727847376,"remaining_time":21.40678711},
{"learn":[0.2994774877],"iteration":55,"passed_time":6.85214811,"remaining_time":21.29060306},
{"learn":[0.2980930047],"iteration":56,"passed_time":6.955704322,"remaining_time":21.11117277},
{"learn":[0.2967053608],"iteration":57,"passed_time":7.112708446,"remaining_time":21.09285953},
{"learn":[0.2958801912],"iteration":58,"passed_time":7.342118238,"remaining_time":21.27969862},
{"learn":[0.2950228721],"iteration":59,"passed_time":7.465275556,"remaining_time":21.15161408},
{"learn":[0.2935786904],"iteration":60,"passed_time":7.612498654,"remaining_time":21.09036512},
{"learn":[0.292816509],"iteration":61,"passed_time":7.718636246,"remaining_time":20.91501434},
{"learn":[0.2915698242],"iteration":62,"passed_time":7.84018032,"remaining_time":20.78270021},
{"learn":[0.2906331209],"iteration":63,"passed_time":8.032170031,"remaining_time":20.83344102},
{"learn":[0.2894996145],"iteration":64,"passed_time":8.191629345,"remaining_time":20.79413603},
{"learn":[0.2885441509],"iteration":65,"passed_time":8.305401935,"remaining_time":20.63766541},
{"learn":[0.2872804533],"iteration":66,"passed_time":8.442071949,"remaining_time":20.53817504},
{"learn":[0.2858422595],"iteration":67,"passed_time":8.565285909,"remaining_time":20.40553408},
{"learn":[0.2851241519],"iteration":68,"passed_time":8.650220417,"remaining_time":20.18384764},
{"learn":[0.2843137336],"iteration":69,"passed_time":8.767432142,"remaining_time":20.0398449},
{"learn":[0.2830568976],"iteration":70,"passed_time":8.925994309,"remaining_time":19.98919852},
{"learn":[0.2814479595],"iteration":71,"passed_time":9.03240731,"remaining_time":19.82111604},
{"learn":[0.2807748766],"iteration":72,"passed_time":9.1100881,"remaining_time":19.5929292},
{"learn":[0.2799861225],"iteration":73,"passed_time":9.219289125,"remaining_time":19.43525816},
{"learn":[0.2794260896],"iteration":74,"passed_time":9.343683297,"remaining_time":19.31027881},
{"learn":[0.2787328845],"iteration":75,"passed_time":9.596380928,"remaining_time":19.4452982},
{"learn":[0.2776847759],"iteration":76,"passed_time":9.731501625,"remaining_time":19.33662011},
{"learn":[0.2770183748],"iteration":77,"passed_time":9.831930969,"remaining_time":19.15966035},
{"learn":[0.275886359],"iteration":78,"passed_time":10.06002551,"remaining_time":19.22865635},
{"learn":[0.2749262181],"iteration":79,"passed_time":10.18036353,"remaining_time":19.08818162},
{"learn":[0.2743431846],"iteration":80,"passed_time":10.30295649,"remaining_time":18.95235207},
{"learn":[0.2738301038],"iteration":81,"passed_time":10.6845785,"remaining_time":19.2843612},
{"learn":[0.273191766],"iteration":82,"passed_time":10.98076199,"remaining_time":19.44785556},
{"learn":[0.2722217054],"iteration":83,"passed_time":11.10950899,"remaining_time":19.30938468},
{"learn":[0.2714089741],"iteration":84,"passed_time":11.28731282,"remaining_time":19.25482776},
{"learn":[0.2705527858],"iteration":85,"passed_time":11.44782957,"remaining_time":19.16845881},
{"learn":[0.2700376491],"iteration":86,"passed_time":11.57903256,"remaining_time":19.03220295},
{"learn":[0.2695162675],"iteration":87,"passed_time":11.6776693,"remaining_time":18.84351183},
{"learn":[0.2686015625],"iteration":88,"passed_time":11.76717697,"remaining_time":18.64238148},
{"learn":[0.2679929071],"iteration":89,"passed_time":11.87230381,"remaining_time":18.46802814},
{"learn":[0.2676423982],"iteration":90,"passed_time":11.9849463,"remaining_time":18.30667622},
{"learn":[0.2666372327],"iteration":91,"passed_time":12.11131895,"remaining_time":18.16697842},
{"learn":[0.266050884],"iteration":92,"passed_time":12.20672596,"remaining_time":17.98195114},
{"learn":[0.2654762284],"iteration":93,"passed_time":12.30742134,"remaining_time":17.80648194},
{"learn":[0.2649932669],"iteration":94,"passed_time":12.41419762,"remaining_time":17.6412282},
{"learn":[0.2645886359],"iteration":95,"passed_time":12.5179604,"remaining_time":17.4729864},
{"learn":[0.2638435701],"iteration":96,"passed_time":12.62474091,"remaining_time":17.31021177},
{"learn":[0.2632757504],"iteration":97,"passed_time":12.73425802,"remaining_time":17.1522659},
{"learn":[0.2626095806],"iteration":98,"passed_time":12.84985063,"remaining_time":17.0033377},
{"learn":[0.2622319593],"iteration":99,"passed_time":13.01730757,"remaining_time":16.92249984},
{"learn":[0.2615243627],"iteration":100,"passed_time":13.1306465,"remaining_time":16.77082572},
{"learn":[0.2611085012],"iteration":101,"passed_time":13.28356872,"remaining_time":16.66957644},
{"learn":[0.2606958779],"iteration":102,"passed_time":13.3921004,"remaining_time":16.51258981},
{"learn":[0.2599085629],"iteration":103,"passed_time":13.48012568,"remaining_time":16.33169073},
{"learn":[0.2590677426],"iteration":104,"passed_time":13.58449697,"remaining_time":16.1720202},
{"learn":[0.2587177734],"iteration":105,"passed_time":13.67551013,"remaining_time":15.99776657},
{"learn":[0.2580368781],"iteration":106,"passed_time":13.80718781,"remaining_time":15.87181402},
{"learn":[0.2575228721],"iteration":107,"passed_time":13.91763469,"remaining_time":15.72177252},
{"learn":[0.2568354749],"iteration":108,"passed_time":14.00878945,"remaining_time":15.5510415},
{"learn":[0.256249229],"iteration":109,"passed_time":14.09761153,"remaining_time":15.37921258},
{"learn":[0.2556904297],"iteration":110,"passed_time":14.24821806,"remaining_time":15.27511666},
{"learn":[0.2552916324],"iteration":111,"passed_time":14.31747723,"remaining_time":15.08448494},
{"learn":[0.2546373869],"iteration":112,"passed_time":14.43753061,"remaining_time":14.94859364},
{"learn":[0.2539436421],"iteration":113,"passed_time":14.59007975,"remaining_time":14.84604606},
{"learn":[0.2532635434],"iteration":114,"passed_time":14.7652813,"remaining_time":14.7652813},
{"learn":[0.2527367907],"iteration":115,"passed_time":15.00793092,"remaining_time":14.74917349},
{"learn":[0.2524363692],"iteration":116,"passed_time":15.15969076,"remaining_time":14.64141074},
{"learn":[0.251844778],"iteration":117,"passed_time":15.34475554,"remaining_time":14.56451373},
{"learn":[0.2512566046],"iteration":118,"passed_time":15.51955693,"remaining_time":14.47622537},
{"learn":[0.2508311061],"iteration":119,"passed_time":15.69083231,"remaining_time":14.38326295}
]}"learn":[0.240846167],"iteration":120,"passed_time":14.95165535,"remaining_time":13.46884655},
{"learn":[0.2404583962],"iteration":121,"passed_time":15.06883133,"remaining_time":13.33962117},
{"learn":[0.2399861163],"iteration":122,"passed_time":15.15912324,"remaining_time":13.18720477},
{"learn":[0.2397641901],"iteration":123,"passed_time":15.25706295,"remaining_time":13.04232801},
{"learn":[0.239447789],"iteration":124,"passed_time":15.36594771,"remaining_time":12.90739607},
{"learn":[0.2387754791],"iteration":125,"passed_time":15.46034725,"remaining_time":12.76092154},
{"learn":[0.2385342908],"iteration":126,"passed_time":15.60375342,"remaining_time":12.65501261},
{"learn":[0.2381037016],"iteration":127,"passed_time":15.73842592,"remaining_time":12.54155815},
{"learn":[0.2377593706],"iteration":128,"passed_time":15.81326501,"remaining_time":12.38092842},
{"learn":[0.2372804407],"iteration":129,"passed_time":15.89939624,"remaining_time":12.2303048},
{"learn":[0.2367487688],"iteration":130,"passed_time":15.97638743,"remaining_time":12.07375844},
{"learn":[0.236042722],"iteration":131,"passed_time":16.05933528,"remaining_time":11.92283983},
{"learn":[0.2356331976],"iteration":132,"passed_time":16.1664675,"remaining_time":11.79058156},
{"learn":[0.2353296601],"iteration":133,"passed_time":16.29694705,"remaining_time":11.67542475},
{"learn":[0.2350189789],"iteration":134,"passed_time":16.45398297,"remaining_time":11.57872876},
{"learn":[0.2342868972],"iteration":135,"passed_time":16.67973191,"remaining_time":11.52863823},
{"learn":[0.2339958383],"iteration":136,"passed_time":16.90240904,"remaining_time":11.47389811},
{"learn":[0.2336170941],"iteration":137,"passed_time":17.05866759,"remaining_time":11.37244506},
{"learn":[0.2330966048],"iteration":138,"passed_time":17.2821785,"remaining_time":11.31423197},
{"learn":[0.2322840069],"iteration":139,"passed_time":17.47617873,"remaining_time":11.23468632},
{"learn":[0.231528971],"iteration":140,"passed_time":17.57110765,"remaining_time":11.09098284},
{"learn":[0.2312472327],"iteration":141,"passed_time":17.64033994,"remaining_time":10.93204165},
{"learn":[0.2305035106],"iteration":142,"passed_time":17.69602565,"remaining_time":10.76611351},
{"learn":[0.2298570186],"iteration":143,"passed_time":17.74345963,"remaining_time":10.59678839}
]}":10.19636275},
{"learn":[0.2263232165],"iteration":144,"passed_time":17.18720031,"remaining_time":10.07525535},
{"learn":[0.2259444387],"iteration":145,"passed_time":17.2959603,"remaining_time":9.951100447},
{"learn":[0.2254982011],"iteration":146,"passed_time":17.39698685,"remaining_time":9.822788496},
{"learn":[0.2252074424],"iteration":147,"passed_time":17.5117242,"remaining_time":9.702441788},
{"learn":[0.2249094881],"iteration":148,"passed_time":17.62764367,"remaining_time":9.582813},
{"learn":[0.2246098376],"iteration":149,"passed_time":17.7189009,"remaining_time":9.45008048},
{"learn":[0.223979852],"iteration":150,"passed_time":17.80830521,"remaining_time":9.31692789},
{"learn":[0.2236646279],"iteration":151,"passed_time":17.91932886,"remaining_time":9.195445072},
{"learn":[0.2230722656],"iteration":152,"passed_time":18.04094059,"remaining_time":9.079427618},
{"learn":[0.2226658357],"iteration":153,"passed_time":18.12325566,"remaining_time":8.943944352},
{"learn":[0.2224302015],"iteration":154,"passed_time":18.25918488,"remaining_time":8.835089459},
{"learn":[0.2217877775],"iteration":155,"passed_time":18.41535006,"remaining_time":8.735486566},
{"learn":[0.2215334087],"iteration":156,"passed_time":18.70254691,"remaining_time":8.696088693},
{"learn":[0.2213677529],"iteration":157,"passed_time":18.93847311,"remaining_time":8.630190279},
{"learn":[0.2208707854],"iteration":158,"passed_time":19.12492117,"remaining_time":8.540059141}
]}rn":[0.2244999146],"iteration":159,"passed_time":16.06414718,"remaining_time":7.028064389},
{"learn":[0.2241468532],"iteration":160,"passed_time":16.14805844,"remaining_time":6.920596475},
{"learn":[0.223751366],"iteration":161,"passed_time":16.37555562,"remaining_time":6.873690013},
{"learn":[0.2231989717],"iteration":162,"passed_time":16.51717086,"remaining_time":6.789266551},
{"learn":[0.2229631001],"iteration":163,"passed_time":16.62444665,"remaining_time":6.690326092},
{"learn":[0.2224316726],"iteration":164,"passed_time":16.71786462,"remaining_time":6.585825455},
{"learn":[0.2221066504],"iteration":165,"passed_time":16.81538457,"remaining_time":6.483039835},
{"learn":[0.2218222301],"iteration":166,"passed_time":16.896997,"remaining_time":6.374316232},
{"learn":[0.2215073473],"iteration":167,"passed_time":16.9736466,"remaining_time":6.264083866},
{"learn":[0.2212244563],"iteration":168,"passed_time":17.15339622,"remaining_time":6.19146254},
{"learn":[0.2208797438],"iteration":169,"passed_time":17.30924723,"remaining_time":6.109146081},
{"learn":[0.2207507611],"iteration":170,"passed_time":17.32585094,"remaining_time":5.977925179},
{"learn":[0.2203933603],"iteration":171,"passed_time":17.45187294,"remaining_time":5.884933899},
{"learn":[0.2199758165],"iteration":172,"passed_time":17.61247382,"remaining_time":5.802953802},
{"learn":[0.2194891552],"iteration":173,"passed_time":17.84518308,"remaining_time":5.743277314},
{"learn":[0.2189784618],"iteration":174,"passed_time":17.97695984,"remaining_time":5.649901663},
{"learn":[0.2187206463],"iteration":175,"passed_time":18.08688805,"remaining_time":5.549386105},
{"learn":[0.2181503772],"iteration":176,"passed_time":18.28336182,"remaining_time":5.474678963},
{"learn":[0.2177547654],"iteration":177,"passed_time":18.44775194,"remaining_time":5.389230903},
{"learn":[0.217506299],"iteration":178,"passed_time":18.5606693,"remaining_time":5.288235388},
{"learn":[0.217190891],"iteration":179,"passed_time":18.89974576,"remaining_time":5.249929377},
{"learn":[0.2167580126],"iteration":180,"passed_time":19.22339806,"remaining_time":5.204124336},
{"learn":[0.2164605856],"iteration":181,"passed_time":19.31641,"remaining_time":5.094437802},
{"learn":[0.2161204222],"iteration":182,"passed_time":19.5062585,"remaining_time":5.009804096},
{"learn":[0.2156360883],"iteration":183,"passed_time":19.59476085,"remaining_time":4.898690213},
{"learn":[0.2151802892],"iteration":184,"passed_time":19.72587866,"remaining_time":4.798186702},
{"learn":[0.2147813519],"iteration":185,"passed_time":19.83943557,"remaining_time":4.693199813},
{"learn":[0.2145495533],"iteration":186,"passed_time":19.95469202,"remaining_time":4.588512068},
{"learn":[0.2142070887],"iteration":187,"passed_time":20.05720144,"remaining_time":4.480864151},
{"learn":[0.2133771264],"iteration":188,"passed_time":20.20770484,"remaining_time":4.383682003},
{"learn":[0.2130663878],"iteration":189,"passed_time":20.32766269,"remaining_time":4.279507935},
{"learn":[0.2127539307],"iteration":190,"passed_time":20.44830854,"remaining_time":4.175309074},
{"learn":[0.2123262201],"iteration":191,"passed_time":20.57645516,"remaining_time":4.072423417},
{"learn":[0.2121075714],"iteration":192,"passed_time":20.6799116,"remaining_time":3.964542639},
{"learn":[0.211913698],"iteration":193,"passed_time":20.78444951,"remaining_time":3.856908156},
{"learn":[0.2113772046],"iteration":194,"passed_time":20.91376324,"remaining_time":3.753752376},
{"learn":[0.2110786255],"iteration":195,"passed_time":21.01378534,"remaining_time":3.645248477},
{"learn":[0.2107220971],"iteration":196,"passed_time":21.11121475,"remaining_time":3.536396379},
{"learn":[0.2102080806],"iteration":197,"passed_time":21.3545513,"remaining_time":3.451240613},
{"learn":[0.2100325901],"iteration":198,"passed_time":21.50894573,"remaining_time":3.350639787},
{"learn":[0.2094044891],"iteration":199,"passed_time":21.60871524,"remaining_time":3.241307285},
{"learn":[0.2090716075],"iteration":200,"passed_time":21.69889136,"remaining_time":3.130685817},
{"learn":[0.208788812],"iteration":201,"passed_time":21.78780346,"remaining_time":3.020091568},
{"learn":[0.2082113251],"iteration":202,"passed_time":21.88643013,"remaining_time":2.911003023},
{"learn":[0.2080831095],"iteration":203,"passed_time":22.00979938,"remaining_time":2.80517051},
{"learn":[0.2075363972],"iteration":204,"passed_time":22.11362289,"remaining_time":2.696783279},
{"learn":[0.2070728921],"iteration":205,"passed_time":22.20629458,"remaining_time":2.587141117},
{"learn":[0.2066201758],"iteration":206,"passed_time":22.29960165,"remaining_time":2.477733517},
{"learn":[0.2062821028],"iteration":207,"passed_time":22.37777511,"remaining_time":2.366880059},
{"learn":[0.2060562531],"iteration":208,"passed_time":22.46866645,"remaining_time":2.257617204},
{"learn":[0.2058216653],"iteration":209,"passed_time":22.5452202,"remaining_time":2.147163828},
{"learn":[0.2053207971],"iteration":210,"passed_time":22.64005564,"remaining_time":2.038677996},
{"learn":[0.2052687493],"iteration":211,"passed_time":22.68195843,"remaining_time":1.925826659},
{"learn":[0.2051027543],"iteration":212,"passed_time":22.83698636,"remaining_time":1.822670273},
{"learn":[0.204687117],"iteration":213,"passed_time":23.00585559,"remaining_time":1.720063969},
{"learn":[0.2040820852],"iteration":214,"passed_time":23.21770154,"remaining_time":1.619839642},
{"learn":[0.2035286019],"iteration":215,"passed_time":23.3844644,"remaining_time":1.51565973},
{"learn":[0.2032728749],"iteration":216,"passed_time":23.57935215,"remaining_time":1.412587917},
{"learn":[0.2029103373],"iteration":217,"passed_time":23.7968438,"remaining_time":1.309918007},
{"learn":[0.2023240786],"iteration":218,"passed_time":24.04106341,"remaining_time":1.207541998},
{"learn":[0.2021515076],"iteration":219,"passed_time":24.11817722,"remaining_time":1.096280783},
{"learn":[0.2016085253],"iteration":220,"passed_time":24.23068382,"remaining_time":0.9867699294}
]}